dpk_doc_id/__init__.py
dpk_doc_id/local.py
dpk_doc_id/local_python.py
dpk_doc_id/transform.py
dpk_doc_id/transform_python.py
dpk_doc_id/ray/__init__.py
dpk_doc_id/ray/local.py
dpk_doc_id/ray/s3.py
dpk_doc_id/ray/transform.py
dpk_doc_id/spark/__init__.py
dpk_doc_id/spark/local.py
dpk_doc_id/spark/transform.py
dpk_doc_quality/__init__.py
dpk_doc_quality/cc_net_prepro.py
dpk_doc_quality/doc_Gopher_statistics.py
dpk_doc_quality/doc_c4_statistics.py
dpk_doc_quality/local.py
dpk_doc_quality/local_python.py
dpk_doc_quality/transform.py
dpk_doc_quality/transform_python.py
dpk_doc_quality/utils.py
dpk_doc_quality/ldnoobw/de
dpk_doc_quality/ldnoobw/en
dpk_doc_quality/ldnoobw/es
dpk_doc_quality/ldnoobw/fr
dpk_doc_quality/ldnoobw/ja
dpk_doc_quality/ldnoobw/pt
dpk_doc_quality/ray/__init__.py
dpk_doc_quality/ray/local.py
dpk_doc_quality/ray/s3.py
dpk_doc_quality/ray/transform.py
dpk_ededup/__init__.py
dpk_ededup/local.py
dpk_ededup/local_python.py
dpk_ededup/local_python_incremental.py
dpk_ededup/transform_base.py
dpk_ededup/transform_python.py
dpk_ededup/ray/__init__.py
dpk_ededup/ray/cluster_estimator.py
dpk_ededup/ray/local.py
dpk_ededup/ray/local_incremental.py
dpk_ededup/ray/s3.py
dpk_ededup/ray/transform.py
dpk_extreme_tokenized/__init__.py
dpk_extreme_tokenized/common.py
dpk_extreme_tokenized/runtime.py
dpk_extreme_tokenized/transform.py
dpk_extreme_tokenized/ray/__init__.py
dpk_extreme_tokenized/ray/runtime.py
dpk_filter/__init__.py
dpk_filter/local.py
dpk_filter/local_python.py
dpk_filter/test_support.py
dpk_filter/transform.py
dpk_filter/transform_python.py
dpk_filter/ray/__init__.py
dpk_filter/ray/local.py
dpk_filter/ray/s3.py
dpk_filter/ray/transform.py
dpk_filter/spark/local.py
dpk_filter/spark/transform.py
dpk_lang_id/lang_models.py
dpk_lang_id/local.py
dpk_lang_id/local_python.py
dpk_lang_id/nlp.py
dpk_lang_id/transform.py
dpk_lang_id/transform_python.py
dpk_lang_id/ray/local.py
dpk_lang_id/ray/s3.py
dpk_lang_id/ray/transform.py
dpk_readability/__init__.py
data_prep_toolkit_idiud-1.1.0.dist-info/METADATA
data_prep_toolkit_idiud-1.1.0.dist-info/WHEEL
data_prep_toolkit_idiud-1.1.0.dist-info/top_level.txt
data_prep_toolkit_idiud-1.1.0.dist-info/RECORD
